<?xml version='1.0' encoding='UTF-8'?>
<DEFECTS><DEFECT><SFA><FILEPATH>c:\users\omegagomachi\downloads\project 2\quake2-full-master\game\</FILEPATH><FILENAME>m_medic.c</FILENAME><LINE>51</LINE><COLUMN>54</COLUMN></SFA><DEFECTCODE>6011</DEFECTCODE><DESCRIPTION>Dereferencing NULL pointer 'self'. </DESCRIPTION><FUNCTION>medic_FindDeadMonster</FUNCTION><DECORATED>medic_FindDeadMonster</DECORATED><FUNCLINE>46</FUNCLINE><PROBABILITY>1</PROBABILITY><RANK>4</RANK><CATEGORY><RULECATEGORY>mspft</RULECATEGORY></CATEGORY><PATH><SFA><FILEPATH>c:\users\omegagomachi\downloads\project 2\quake2-full-master\game\</FILEPATH><FILENAME>m_medic.c</FILENAME><LINE>48</LINE><COLUMN>10</COLUMN></SFA><SFA><FILEPATH>c:\users\omegagomachi\downloads\project 2\quake2-full-master\game\</FILEPATH><FILENAME>m_medic.c</FILENAME><LINE>49</LINE><COLUMN>10</COLUMN></SFA><SFA><FILEPATH>c:\users\omegagomachi\downloads\project 2\quake2-full-master\game\</FILEPATH><FILENAME>m_medic.c</FILENAME><LINE>51</LINE><COLUMN>54</COLUMN><KEYEVENT><ID>1</ID><KIND>branch</KIND><IMPORTANCE>Full</IMPORTANCE><MESSAGE>Skip this loop, (assume '&lt;branch condition&gt;' is false)</MESSAGE></KEYEVENT></SFA><SFA><FILEPATH>c:\users\omegagomachi\downloads\project 2\quake2-full-master\game\</FILEPATH><FILENAME>m_medic.c</FILENAME><LINE>53</LINE><COLUMN>10</COLUMN><KEYEVENT><ID>2</ID><KIND>branch</KIND><IMPORTANCE>Full</IMPORTANCE><MESSAGE>Skip this branch, (assume 'ent==self' is false)</MESSAGE></KEYEVENT></SFA><SFA><FILEPATH>c:\users\omegagomachi\downloads\project 2\quake2-full-master\game\</FILEPATH><FILENAME>m_medic.c</FILENAME><LINE>55</LINE><COLUMN>6</COLUMN><KEYEVENT><ID>3</ID><KIND>branch</KIND><IMPORTANCE>Full</IMPORTANCE><MESSAGE>Skip this branch, (assume '!((ent-&gt;svflags&amp;4))' is false)</MESSAGE></KEYEVENT></SFA><SFA><FILEPATH>c:\users\omegagomachi\downloads\project 2\quake2-full-master\game\</FILEPATH><FILENAME>m_medic.c</FILENAME><LINE>57</LINE><COLUMN>31</COLUMN><KEYEVENT><ID>4</ID><KIND>branch</KIND><IMPORTANCE>Full</IMPORTANCE><MESSAGE>Skip this branch, (assume 'ent-&gt;monsterinfo.aiflags' is false)</MESSAGE></KEYEVENT></SFA><SFA><FILEPATH>c:\users\omegagomachi\downloads\project 2\quake2-full-master\game\</FILEPATH><FILENAME>m_medic.c</FILENAME><LINE>59</LINE><COLUMN>9</COLUMN><KEYEVENT><ID>5</ID><KIND>branch</KIND><IMPORTANCE>Full</IMPORTANCE><MESSAGE>Skip this branch, (assume 'ent-&gt;owner' is false)</MESSAGE></KEYEVENT></SFA><SFA><FILEPATH>c:\users\omegagomachi\downloads\project 2\quake2-full-master\game\</FILEPATH><FILENAME>m_medic.c</FILENAME><LINE>61</LINE><COLUMN>18</COLUMN><KEYEVENT><ID>6</ID><KIND>branch</KIND><IMPORTANCE>Full</IMPORTANCE><MESSAGE>Skip this branch, (assume 'ent-&gt;health&gt;0' is false)</MESSAGE></KEYEVENT></SFA><SFA><FILEPATH>c:\users\omegagomachi\downloads\project 2\quake2-full-master\game\</FILEPATH><FILENAME>m_medic.c</FILENAME><LINE>63</LINE><COLUMN>9</COLUMN><KEYEVENT><ID>7</ID><KIND>branch</KIND><IMPORTANCE>Full</IMPORTANCE><MESSAGE>Skip this branch, (assume 'ent-&gt;nextthink' is false)</MESSAGE></KEYEVENT></SFA><SFA><FILEPATH>c:\users\omegagomachi\downloads\project 2\quake2-full-master\game\</FILEPATH><FILENAME>m_medic.c</FILENAME><LINE>65</LINE><COLUMN>6</COLUMN><KEYEVENT><ID>8</ID><KIND>declaration</KIND><IMPORTANCE>Full</IMPORTANCE><MESSAGE>'self' is an In/Out argument to 'visible' (declared at c:\users\omegagomachi\downloads\project 2\quake2-full-master\game\g_local.h:721)</MESSAGE></KEYEVENT></SFA><SFA><FILEPATH>c:\users\omegagomachi\downloads\project 2\quake2-full-master\game\</FILEPATH><FILENAME>m_medic.c</FILENAME><LINE>65</LINE><COLUMN>6</COLUMN><KEYEVENT><ID>9</ID><KIND>branch</KIND><IMPORTANCE>Full</IMPORTANCE><MESSAGE>Skip this branch, (assume '!visible(self, ent)' is false)</MESSAGE></KEYEVENT></SFA><SFA><FILEPATH>c:\users\omegagomachi\downloads\project 2\quake2-full-master\game\</FILEPATH><FILENAME>m_medic.c</FILENAME><LINE>67</LINE><COLUMN>6</COLUMN><KEYEVENT><ID>10</ID><KIND>branch</KIND><IMPORTANCE>Full</IMPORTANCE><MESSAGE>Enter this branch, (assume '!best')</MESSAGE></KEYEVENT></SFA><SFA><FILEPATH>c:\users\omegagomachi\downloads\project 2\quake2-full-master\game\</FILEPATH><FILENAME>m_medic.c</FILENAME><LINE>69</LINE><COLUMN>8</COLUMN></SFA><SFA><FILEPATH>c:\users\omegagomachi\downloads\project 2\quake2-full-master\game\</FILEPATH><FILENAME>m_medic.c</FILENAME><LINE>51</LINE><COLUMN>54</COLUMN><KEYEVENT><ID>11</ID><KIND>branch</KIND><IMPORTANCE>Full</IMPORTANCE><MESSAGE>Enter this loop, (assume '&lt;branch condition&gt;')</MESSAGE></KEYEVENT></SFA><SFA><FILEPATH>c:\users\omegagomachi\downloads\project 2\quake2-full-master\game\</FILEPATH><FILENAME>m_medic.c</FILENAME><LINE>51</LINE><COLUMN>54</COLUMN><KEYEVENT><ID>12</ID><KIND>usage</KIND><IMPORTANCE>Essential</IMPORTANCE><MESSAGE>'self' is dereferenced, but may still be NULL</MESSAGE></KEYEVENT></SFA></PATH></DEFECT></DEFECTS>