<?xml version='1.0' encoding='UTF-8'?>
<DEFECTS><DEFECT><SFA><FILEPATH>c:\users\omegagomachi\downloads\project 2\quake2-full-master\client\</FILEPATH><FILENAME>keys.c</FILENAME><LINE>252</LINE><COLUMN>9</COLUMN></SFA><DEFECTCODE>6031</DEFECTCODE><DESCRIPTION>Return value ignored: 'strtok'.</DESCRIPTION><FUNCTION>Key_Console</FUNCTION><DECORATED>Key_Console</DECORATED><FUNCLINE>194</FUNCLINE><PATH/></DEFECT><DEFECT><SFA><FILEPATH>c:\users\omegagomachi\downloads\project 2\quake2-full-master\client\</FILEPATH><FILENAME>keys.c</FILENAME><LINE>243</LINE><COLUMN>15</COLUMN></SFA><DEFECTCODE>28278</DEFECTCODE><DESCRIPTION>Function toupper appears with no prototype in scope.  Only limited analysis can be performed. Include the appropriate header or add a prototype. This warning also occurs if parameter or return types are omitted in a function definition.</DESCRIPTION><FUNCTION>Key_Console</FUNCTION><DECORATED>Key_Console</DECORATED><FUNCLINE>194</FUNCLINE><PATH/></DEFECT><DEFECT><SFA><FILEPATH>c:\users\omegagomachi\downloads\project 2\quake2-full-master\client\</FILEPATH><FILENAME>keys.c</FILENAME><LINE>343</LINE><COLUMN>9</COLUMN></SFA><DEFECTCODE>6385</DEFECTCODE><DESCRIPTION>Reading invalid data from 'key_lines':  the readable size is '8192' bytes, but 'edit_line' bytes may be read.</DESCRIPTION><FUNCTION>Key_Console</FUNCTION><DECORATED>Key_Console</DECORATED><FUNCLINE>194</FUNCLINE><PROBABILITY>1</PROBABILITY><RANK>4</RANK><CATEGORY><RULECATEGORY>mspft</RULECATEGORY></CATEGORY><PATH><SFA><FILEPATH>c:\users\omegagomachi\downloads\project 2\quake2-full-master\client\</FILEPATH><FILENAME>keys.c</FILENAME><LINE>197</LINE><COLUMN>10</COLUMN><KEYEVENT><ID>1</ID><KIND>branch</KIND><IMPORTANCE>Full</IMPORTANCE><MESSAGE>Assume switch ( 'key' ) resolves to the default case</MESSAGE></KEYEVENT></SFA><SFA><FILEPATH>c:\users\omegagomachi\downloads\project 2\quake2-full-master\client\</FILEPATH><FILENAME>keys.c</FILENAME><LINE>243</LINE><COLUMN>51</COLUMN><KEYEVENT><ID>2</ID><KIND>branch</KIND><IMPORTANCE>Full</IMPORTANCE><MESSAGE>Skip this branch, (assume '&lt;branch condition&gt;' is false)</MESSAGE></KEYEVENT></SFA><SFA><FILEPATH>c:\users\omegagomachi\downloads\project 2\quake2-full-master\client\</FILEPATH><FILENAME>keys.c</FILENAME><LINE>270</LINE><COLUMN>10</COLUMN><KEYEVENT><ID>3</ID><KIND>branch</KIND><IMPORTANCE>Full</IMPORTANCE><MESSAGE>Skip this branch, (assume 'key==108' is false)</MESSAGE></KEYEVENT></SFA><SFA><FILEPATH>c:\users\omegagomachi\downloads\project 2\quake2-full-master\client\</FILEPATH><FILENAME>keys.c</FILENAME><LINE>279</LINE><COLUMN>21</COLUMN><KEYEVENT><ID>4</ID><KIND>branch</KIND><IMPORTANCE>Full</IMPORTANCE><MESSAGE>Skip this branch, (assume 'key==13||key==169' is false)</MESSAGE></KEYEVENT></SFA><SFA><FILEPATH>c:\users\omegagomachi\downloads\project 2\quake2-full-master\client\</FILEPATH><FILENAME>keys.c</FILENAME><LINE>298</LINE><COLUMN>9</COLUMN><KEYEVENT><ID>5</ID><KIND>branch</KIND><IMPORTANCE>Full</IMPORTANCE><MESSAGE>Skip this branch, (assume 'key==9' is false)</MESSAGE></KEYEVENT></SFA><SFA><FILEPATH>c:\users\omegagomachi\downloads\project 2\quake2-full-master\client\</FILEPATH><FILENAME>keys.c</FILENAME><LINE>304</LINE><COLUMN>84</COLUMN><KEYEVENT><ID>6</ID><KIND>branch</KIND><IMPORTANCE>Full</IMPORTANCE><MESSAGE>Skip this branch, (assume '&lt;branch condition&gt;' is false)</MESSAGE></KEYEVENT></SFA><SFA><FILEPATH>c:\users\omegagomachi\downloads\project 2\quake2-full-master\client\</FILEPATH><FILENAME>keys.c</FILENAME><LINE>311</LINE><COLUMN>54</COLUMN><KEYEVENT><ID>7</ID><KIND>branch</KIND><IMPORTANCE>Full</IMPORTANCE><MESSAGE>Skip this branch, (assume '&lt;branch condition&gt;' is false)</MESSAGE></KEYEVENT></SFA><SFA><FILEPATH>c:\users\omegagomachi\downloads\project 2\quake2-full-master\client\</FILEPATH><FILENAME>keys.c</FILENAME><LINE>326</LINE><COLUMN>58</COLUMN><KEYEVENT><ID>8</ID><KIND>branch</KIND><IMPORTANCE>Full</IMPORTANCE><MESSAGE>Enter this branch, (assume '&lt;branch condition&gt;')</MESSAGE></KEYEVENT></SFA><SFA><FILEPATH>c:\users\omegagomachi\downloads\project 2\quake2-full-master\client\</FILEPATH><FILENAME>keys.c</FILENAME><LINE>329</LINE><COLUMN>19</COLUMN><KEYEVENT><ID>9</ID><KIND>branch</KIND><IMPORTANCE>Full</IMPORTANCE><MESSAGE>Skip this branch, (assume 'history_line==edit_line' is false)</MESSAGE></KEYEVENT></SFA><SFA><FILEPATH>c:\users\omegagomachi\downloads\project 2\quake2-full-master\client\</FILEPATH><FILENAME>keys.c</FILENAME><LINE>332</LINE><COLUMN>16</COLUMN></SFA><SFA><FILEPATH>c:\users\omegagomachi\downloads\project 2\quake2-full-master\client\</FILEPATH><FILENAME>keys.c</FILENAME><LINE>335</LINE><COLUMN>3</COLUMN><KEYEVENT><ID>10</ID><KIND>branch</KIND><IMPORTANCE>Full</IMPORTANCE><MESSAGE>Skip this loop, (assume '&lt;branch condition&gt;' is false)</MESSAGE></KEYEVENT></SFA><SFA><FILEPATH>c:\users\omegagomachi\downloads\project 2\quake2-full-master\client\</FILEPATH><FILENAME>keys.c</FILENAME><LINE>336</LINE><COLUMN>19</COLUMN><KEYEVENT><ID>11</ID><KIND>branch</KIND><IMPORTANCE>Full</IMPORTANCE><MESSAGE>Skip this branch, (assume 'history_line==edit_line' is false)</MESSAGE></KEYEVENT></SFA><SFA><FILEPATH>c:\users\omegagomachi\downloads\project 2\quake2-full-master\client\</FILEPATH><FILENAME>keys.c</FILENAME><LINE>343</LINE><COLUMN>9</COLUMN><KEYEVENT><ID>12</ID><KIND>declaration</KIND><IMPORTANCE>Full</IMPORTANCE><MESSAGE>'key_lines' is an In/Out argument to 'strcpy' (declared at &lt;no file&gt;:0)</MESSAGE></KEYEVENT></SFA><SFA><FILEPATH>c:\users\omegagomachi\downloads\project 2\quake2-full-master\client\</FILEPATH><FILENAME>keys.c</FILENAME><LINE>343</LINE><COLUMN>9</COLUMN><KEYEVENT><ID>13</ID><KIND>usage</KIND><IMPORTANCE>Essential</IMPORTANCE><MESSAGE>Invalid read from 'key_lines[32]', (readable range is 0 to 31)</MESSAGE></KEYEVENT></SFA></PATH></DEFECT></DEFECTS>